README
setup.py
aircable_library_op.egg-info/PKG-INFO
aircable_library_op.egg-info/SOURCES.txt
aircable_library_op.egg-info/dependency_links.txt
aircable_library_op.egg-info/not-zip-safe
aircable_library_op.egg-info/requires.txt
aircable_library_op.egg-info/top_level.txt
net/__init__.py
net/aircable/__init__.py
net/aircable/autoreload.py
net/aircable/const.py
net/aircable/fields.py
net/aircable/procworker.py
net/aircable/sdp.py
net/aircable/utils.py
net/aircable/wrappers.py
net/aircable/openproximity/__init__.py
net/aircable/openproximity/pluginsystem.py
net/aircable/openproximity/signals/__init__.py
net/aircable/openproximity/signals/scanner.py
net/aircable/openproximity/signals/uploader.py
net/aircable/spp/__init__.py
net/aircable/spp/errors.py
net/aircable/spp/sppBase.py
net/aircable/spp/sppClient.py
net/aircable/spp/sppServer.py