Metadata-Version: 1.0
Name: aircable-library-op
Version: 0.1.2
Summary: AIRcable libraries for BlueZ Development
Home-page: https://github.com/OpenProximity/aircable-library
Author: Manuel Francisco Naranjo
Author-email: manuel@aircable.net
License: UNKNOWN
Platform: UNKNOWN
Classifier: Development Status :: 5 - Production/Stable
Classifier: Environment :: Console
Classifier: Intended Audience :: Developers
Classifier: License :: OSI Approved :: MIT License
Classifier: Operating System :: OS Independent
Classifier: Programming Language :: Python
Classifier: Framework :: Django
